setup.py
gametex_django_print/__init__.py
gametex_django_print/latex.py
gametex_django_print/models.py
gametex_django_print/tests.py
gametex_django_print/urls.py
gametex_django_print/views.py
gametex_django_print.egg-info/PKG-INFO
gametex_django_print.egg-info/SOURCES.txt
gametex_django_print.egg-info/dependency_links.txt
gametex_django_print.egg-info/requires.txt
gametex_django_print.egg-info/top_level.txt