Metadata-Version: 1.0
Name: gametex-django-print
Version: 0.1.0
Summary: Generate PDFs from GameTeX in Django
Home-page: http://github.com/ternus/gametex-print
Author: Christian Ternus
Author-email: ternus@cternus.net
License: Creative Commons Attribution-Noncommercial-Share Alike license
Platform: UNKNOWN
